cs207rbtree
