Metadata-Version: 1.1
Name: cs207rbtree
Version: 1.0.2
Summary: A red-black tree implemented key-value database
Home-page: https://github.com/rubix-cube/cs207project
Author: rubix-cube
Author-email: UNKNOWN
License: UNKNOWN
Platform: UNKNOWN
Classifier: Development Status :: 3 - Alpha
Classifier: Programming Language :: Python :: 3.5
